dochubproto/__init__.py
dochubproto/dochubproto.py
dochubproto/sections.py
dochubproto/templates/_footer.jinja2
dochubproto/templates/_typekit_loader.jinja2
dochubproto/templates/doclist.jinja2
dochubproto/templates/icons.svg
dochubproto/templates/index.jinja2
sqre_dochub_proto-0.0.2.dist-info/DESCRIPTION.rst
sqre_dochub_proto-0.0.2.dist-info/METADATA
sqre_dochub_proto-0.0.2.dist-info/RECORD
sqre_dochub_proto-0.0.2.dist-info/WHEEL
sqre_dochub_proto-0.0.2.dist-info/metadata.json
sqre_dochub_proto-0.0.2.dist-info/top_level.txt
