Metadata-Version: 2.0
Name: sqre-dochub-proto
Version: 0.0.2
Summary: DocHubProto class for creating www.lsst.io index
Home-page: https://github.com/sqre-lsst/dochub-prototype
Author: Adam Thornton
Author-email: athornton@lsst.org
License: MIT
Keywords: lsst
Platform: UNKNOWN
Classifier: Development Status :: 4 - Beta
Classifier: Programming Language :: Python :: 2.7
Classifier: Programming Language :: Python :: 3.5
Classifier: License :: OSI Approved :: MIT License
Requires-Dist: Jinja2 (<3.0.0,>=2.9)
Requires-Dist: pyyaml (<4.0.0,>=3.12)
Requires-Dist: requests (<3.0.0,>=2.13.0)
Requires-Dist: sqre-apikit (>=0.1.1,<1.0.0)
